olg/__init__.py
olg_kitao_sunakawa_and_yamada_2024_chapter6-0.1.0.dist-info/METADATA
olg_kitao_sunakawa_and_yamada_2024_chapter6-0.1.0.dist-info/WHEEL
olg_kitao_sunakawa_and_yamada_2024_chapter6-0.1.0.dist-info/top_level.txt
olg_kitao_sunakawa_and_yamada_2024_chapter6-0.1.0.dist-info/RECORD
