Metadata-Version: 2.4
Name: olg-kitao-sunakawa-and-yamada-2024-chapter6
Version: 0.1.0
Summary: OLG model library
Requires-Python: >=3.8
Requires-Dist: interpolation
Requires-Dist: jupyter
Requires-Dist: matplotlib
Requires-Dist: numba
Requires-Dist: numpy
Requires-Dist: pandas
Requires-Dist: quantecon
Requires-Dist: ruff
Requires-Dist: seaborn>=0.13.2
Requires-Dist: pre-commit
Requires-Dist: japanize-matplotlib>=1.1.3
